verilog_codes/NORMAL/dataMem.v
module dataMem(
    address,
    writeData,
    readData,
    memWrite,
    memRead
);

    input wire memRead; // 1: Read, 0: No Read
    input wire memWrite; // 1: Write, 0: No Write
    input wire [31:0] address;
    input wire [31:0] writeData;
    output reg [31:0] readData;

    reg [31:0] memory [1023:0]; 
    
    always @(address or memRead) begin
        if (memRead == 1'b1) begin
            readData = memory[address[11:2]]; 
        end
    end

    always @(posedge memWrite) begin
        if (memWrite == 1'b1) begin
            memory[address[11:2]] = writeData; // Write data to memory
        end
    end

    integer i;
    initial begin
        for (i = 0; i < 1024; i = i + 1) begin
            memory[i] = 32'b0;
        end
        
// beberapa test value memori
        memory[0] = 32'hA000000A;
        memory[1] = 32'hB000000B;
        memory[2] = 32'hC000000C;
        memory[3] = 32'hD000000D;
    end
endmodule

verilog_codes/NORMAL/adder.v
// module halfAdder

module halfAdder(
  num1,
  num2,
  sum,
  carry
  );
  input num1;
  input num2;
  output sum;
  output carry;
  
  assign sum = num1 ^ num2; // operasi XOR
  assign carry = num1 & num2; // operasi AND

endmodule


// module fullAdder

module fullAdder(
  num1,
  num2,
  carryI,
  sum,
  carryO
  );
  input num1;
  input num2;
  input carryI;
  output sum;
  output carryO;
  
  assign sum = (num1 ^ num2) ^ carryI;
  assign carryO = (num1 & carryI) | (num1 & num2) | (num2 & carryI);

endmodule

verilog_codes/UTS SBM/Soal 1/fullAddSub32.v
module fullAddSub32(
  num1,
  num2,
  op,
  sumO,
  carryO
);

  input [31:0] num1;		// input 1 berukuran 32 bit
  input [31:0] num2;		// input 2 berukuran 32 bit
  input op; 			// sinyal kendali operasi, 0 untuk penjumalahan dan 1 untuk pengurangan
  output [31:0] sumO;		// hasil akhir penjumlahan atau pengurangan
  output carryO;		// nilai carry out
  
// komponen-komponen wire yang digunakan untuk perhitungan
  wire [31:0] sum;		// menyimpan hasil sementara penjumlahan atau pengurangan
  wire [31:0] carry;		// menyimpan nilai carry
  wire [31:0] num2C;		// komplemen untuk pengurangan

// menentukan nilai num2C
// jika op == 1 (pengurangan), maka num2 akan dikomplemen bitwise menjadi ~num2
// jika op == 0 (penjumlahan), maka num2 tetap
  assign num2C = (op == 1'b1) ? ~num2 : num2;

// loop penjumlahan
// menggunakan generate loop untuk membuat 32 instance fullAdder
// untuk bit ke-0, masukkan carry-in adalah op
// untuk bit ke 1-31 masukkan carry-in adalah carry[i-1]

  genvar i;
  generate 
    for (i = 0; i < 32; i = i + 1) begin : gen_block
      if (i == 0) 
        fullAdder addr0 ( num1[i], num2C[i], op, sum[i], carry[i]);
      else
        fullAdder addrN ( num1[i], num2C[i], carry[i-1], sum[i], carry[i]);
    end
  endgenerate

// penyesuaian nilai carry-out
// jika op == 1 (pengurangan), maka carry[31] akan di komplemen
// jika penjumlahan, akan langsung diambil dari carry[31]
  assign carryO = (op == 1'b1) ? ~carry[31] : carry[31];

// nilai akhir penjumlahan atau pengurangan
  assign sumO = sum;
  
endmodule

verilog_codes/UTS SBM/Soal 2/alu.v
`timescale 1ns/1ps

module alu(
    aluSrc,	
    data1,	// data dari register 1
    data2,	// data dari resgiter 2
    imm,	// nilai immediate
    aluCtrl,	// sinyal ALU Control
    result,	// output result
    zero,	// zero flag
    overflow	// overflow flag
);
    input wire aluSrc;		// memilih operand kedua berasal dari data2 atau immediate
    input wire [31:0] data1;	// operand pertama
    input wire [31:0] data2;	// operand kedua jika aluSrc == 0
    input wire [31:0] imm;	// operand immediate jika aluSrc == 1
    input wire [3:0] aluCtrl;

    output reg [31:0] result;	// hasil operasi
    output wire zero;		// zero flag jika hasil == 0
    output wire overflow;

    wire [31:0] d2;	// operand kedua akhir, bisa berasal dari data2 atau imm
    wire [31:0] sum;	// hasil dari operasi add atau sub
    wire carry;		// carry dari full adder
    wire op;		// flag, 1 == sub dan 0 == add

// zero flag
// zero akan bernilai == 1 jika result == 0
    assign zero = (result == 32'b0) ? 1 : 0;

// jika aluCtrl == 2 (SUB) atau == 3 (SUBU), maka merupakan operasi pengurangan (op == 1)
// jika tidak, akan dianggap penjumlahan (op == 0)
    assign op = (aluCtrl == 2) ? 1 : (aluCtrl == 3) ? 1 : 0;

// menentukan nilai operand kedua
// aluSrc == 0, maka operand kedua menggunakan data2
// aluSrc == 1, maka operand kedua menggunakan imm
    assign d2 = (aluSrc == 0) ? data2 : imm;

// mendeteksi overflow
    wire add_overflow, sub_overflow;

// overflow pada penjumlahan bertanda (signed)
    assign add_overflow = ((data1[31] == d2[31]) && (data1[31] != sum[31]));

// overflow pada pengurangan bertanda (signed)
    assign sub_overflow = ((data1[31] != d2[31]) && (data1[31] != sum[31]));
    assign overflow = (aluCtrl == 4'b0000) ? add_overflow : (aluCtrl == 4'b0010) ? sub_overflow : 1'b0;

    fullAddSub32 addsub(.num1(data1), .num2(d2), .op(op), .sumO(sum), .carryO(carry));

// operasi ALU
    always @(*) begin
        case (aluCtrl)
            4'b0000: result = sum;              // ADD
            4'b0001: result = sum;              // ADDU
            4'b0010: result = sum;              // SUB
            4'b0011: result = sum;              // SUBU
            4'b0100: result = data1 & data2;    // AND
            4'b0101: result = data1 | data2;    // OR
            4'b0110: result = data1 << data2;   // SLL
            4'b0111: result = data1 >> data2;   // SRL
            4'b1000: result = (data1 < data2) ? 1 : 0; // SLT
	    4'b1001: result = (data1 == data2) ? 1 : 0; // BEQ
            4'b1010: result = (data1 != data2) ? 1 : 0; // BNE
            default: result = 0;
        endcase
    end
endmodule

verilog_codes/UTS SBM/Soal 2/regsFile.v
module regsFile( 
    rgr1,
    rgr2,
    write,
    rgw1,
    rgw1data,
    rg1data,
    rg2data
);

    input [4:0] rgr1;		// alamat register ke-1
    input [4:0] rgr2;		// alamat register ke-2
    input [4:0] rgw1;		// alamat register tujuan penulisan
    input [31:0]  rgw1data;	// data yang akan ditulis ke rgw1
    input write;		// sinyal tulis atau write enable
    output reg [31:0] rg1data;	// output dari rgr1
    output reg [31:0] rg2data;	// output dari rgr2
    
    reg [31:0] regMem [31:0];	// register memory, ada 32 register masing-masing 32 bit

// proses pembacaan register
// saat rgr1 atau rgr2 berubah nilainya, maka output rg1data atau rg2data akan langsung diperbarui sesuai isi register
  always @(rgr1 or rgr2)
  begin
    rg1data = regMem[rgr1];
    rg2data = regMem[rgr2];
  end

// proses penulisan ke register

  always @(posedge write)
  begin
    if(rgw1 == 5'b0) regMem[0] = 5'b0;
    else regMem[rgw1] = rgw1data;
  end

    integer i;

    initial 
    begin
        //set all register values to reg number 
        for( i = 0; i < 32; i = i + 1 )
            regMem[i] = i;
    end
endmodule

verilog_codes/UTS SBM/Soal 2/NIM_TB.v
`timescale 1ns / 1ps 

module NIM_TB;
    reg [4:0] rgr1, rgr2, rgw1;
    reg [31:0] immediate;
    reg [31:0] address;
    reg memWrite, memRead;
    reg aluSrc, regWrite;
    reg [3:0] aluCtrl;

    wire [31:0] rg1data, rg2data;
    wire [31:0] aluResult;
    wire zero, overflow;
    wire [31:0] memData;

    regsFile rf(
        .rgr1(rgr1),
        .rgr2(rgr2),
        .write(regWrite),
        .rgw1(rgw1),
        .rgw1data(aluResult),
        .rg1data(rg1data),
        .rg2data(rg2data)
    );

    alu alu_unit(
        .aluSrc(aluSrc),
        .data1(rg1data),
        .data2(rg2data),
        .imm(immediate),
        .aluCtrl(aluCtrl),
        .result(aluResult),
        .zero(zero),
        .overflow(overflow)
    );

    dataMem dm(
        .address(address),
        .writeData(aluResult),
        .readData(memData),
        .memWrite(memWrite),
        .memRead(memRead)
    );

    initial begin
        $dumpfile("nim_test.vcd");
        $dumpvars(0, NIM_TB);
    end

    initial begin
        // Inisialisasi semua sinyal kontrol dan register awal
        rgr1 = 0;
        rgr2 = 0;
        rgw1 = 0;
        immediate = 0;
        address = 0;
        memWrite = 0;
        memRead = 0;
        aluSrc = 0;
        regWrite = 0;
        aluCtrl = 0;

        #10;

        $display("\n ***** MENYIMPAN NIM KE REGISTER ***** ");

        aluSrc = 1;
        aluCtrl = 4'b0000;
        rgr1 = 5'd0;

        // Menyimpan digit 5 di register ke-20
        immediate = 32'd5;
        rgw1 = 5'd20;
        #10;
        regWrite = 1;
        #10;
        regWrite = 0;
        #10;
        $display("Digit NIM pertama, yaitu 5 disimpan di register ke-20");

        // Menyimpan digit 2 di register ke-21
        immediate = 32'd2;
        rgw1 = 5'd21;
        #10;
        regWrite = 1;
        #10;
        regWrite = 0;
        #10;
        $display("Digit NIM kedua, yaitu 2 disimpan di register ke-21");

        // Menyimpan digit 2 di register ke-22
        immediate = 32'd2;
        rgw1 = 5'd22;
        #10;
        regWrite = 1;
        #10;
        regWrite = 0;
        #10;
        $display("Digit NIM ketiga, yaitu 2 disimpan di register ke-22");

        // Menyimpan digit 4 di register ke-23 (sebelumnya 6)
        immediate = 32'd4;
        rgw1 = 5'd23;
        #10;
        regWrite = 1;
        #10;
        regWrite = 0;
        #10;
        $display("Digit NIM keempat, yaitu 4 disimpan di register ke-23");

        // Menyimpan digit 7 di register ke-24 (sebelumnya 0)
        immediate = 32'd7;
        rgw1 = 5'd24;
        #10;
        regWrite = 1;
        #10;
        regWrite = 0;
        #10;
        $display("Digit NIM kelima, yaitu 7 disimpan di register ke-24");

        // Menyimpan digit 9 di register ke-25 (sebelumnya 5)
        immediate = 32'd9;
        rgw1 = 5'd25;
        #10;
        regWrite = 1;
        #10;
        regWrite = 0;
        #10;
        $display("Digit NIM keenam, yaitu 9 disimpan di register ke-25");

        // Menginisialisasi register hasil penjumlahan awal (register 31) dengan 0
        immediate = 32'd0;
        rgw1 = 5'd31;
        #10;
        regWrite = 1;
        #10;
        regWrite = 0;
        #10;

        $display("\n ***** PENJUMLAHAN DIGIT NIM ***** ");

        aluSrc = 0;
        aluCtrl = 4'b0000;

        // Penjumlahan: 0 + 5
        rgr1 = 5'd31;  // register hasil
        rgr2 = 5'd20;  // digit pertama
        #10;
        $display("Menjumlahkan nilai register penyimpanan (0) dengan digit pertama");
        $display("Penjumlahan digit 1: %d + %d = %d", rg1data, rg2data, aluResult);

        rgw1 = 5'd31;
        #10;
        regWrite = 1;
        #10;
        regWrite = 0;
        #10;

        // Penjumlahan: hasil sebelumnya + 2 (digit kedua)
        rgr1 = 5'd31;
        rgr2 = 5'd21;
        #10;
        $display("Menjumlahkan hasil sebelumnya dengan digit kedua");
        $display("Penjumlahan digit 2: %d + %d = %d", rg1data, rg2data, aluResult);
        
        rgw1 = 5'd31;
        #10;
        regWrite = 1;
        #10;
        regWrite = 0;
        #10;

        // Penjumlahan: hasil sebelumnya + 2 (digit ketiga)
        rgr1 = 5'd31;
        rgr2 = 5'd22;
        #10;
        $display("Menjumlahkan hasil sebelumnya dengan digit ketiga");
        $display("Penjumlahan digit 3: %d + %d = %d", rg1data, rg2data, aluResult);
        
        rgw1 = 5'd31;
        #10;
        regWrite = 1;
        #10;
        regWrite = 0;
        #10;

        // Penjumlahan: hasil sebelumnya + 4 (digit keempat)
        rgr1 = 5'd31;
        rgr2 = 5'd23;
        #10;
        $display("Menjumlahkan hasil sebelumnya dengan digit keempat");
        $display("Penjumlahan digit 4: %d + %d = %d", rg1data, rg2data, aluResult);
        
        rgw1 = 5'd31;
        #10;
        regWrite = 1;
        #10;
        regWrite = 0;
        #10;

        // Penjumlahan: hasil sebelumnya + 7 (digit kelima)
        rgr1 = 5'd31;
        rgr2 = 5'd24;
        #10;
        $display("Menjumlahkan hasil sebelumnya dengan digit kelima");
        $display("Penjumlahan digit 5: %d + %d = %d", rg1data, rg2data, aluResult);
        
        rgw1 = 5'd31;
        #10;
        regWrite = 1;
        #10;
        regWrite = 0;
        #10;

        // Penjumlahan: hasil sebelumnya + 9 (digit keenam)
        rgr1 = 5'd31;
        rgr2 = 5'd25;
        #10;
        $display("Menjumlahkan hasil sebelumnya dengan digit keenam");
        $display("Penjumlahan digit 6: %d + %d = %d", rg1data, rg2data, aluResult);
        
        rgw1 = 5'd31;
        #10;
        regWrite = 1;
        #10;
        regWrite = 0;
        #10;

        // Menyelesaikan operasi penjumlahan
        rgr1 = 5'd31;
        rgr2 = 5'd0;
        #10;

        rgr1 = 5'd31;
        #60;
        $display("Hasil operasi penjumlahan digit NIM berada di register 31: %d", rg1data);

        address = 32'h0;
        #10;
        memWrite = 1;
        #10;
        memWrite = 0;

        memRead = 1;
        #10;

        $display("Hasil operasi penjumlahan digit NIM berhasil disimpan ke data memory 0: %d", memData);
        $display("Verifikasi: 5 + 2 + 2 + 4 + 7 + 9 = 29");
        $display("\n ***** SELESAI ***** ");
        $finish;
    end
endmodule

verilog_codes/UTS SBM/Soal 2/nim_test.vcd
$date
	Thu Apr 10 12:24:26 2025
$end
$version
	Icarus Verilog
$end
$timescale
	1ps
$end
$scope module NIM_TB $end
$var wire 1 ! zero $end
$var wire 32 " rg2data [31:0] $end
$var wire 32 # rg1data [31:0] $end
$var wire 1 $ overflow $end
$var wire 32 % memData [31:0] $end
$var wire 32 & aluResult [31:0] $end
$var reg 32 ' address [31:0] $end
$var reg 4 ( aluCtrl [3:0] $end
$var reg 1 ) aluSrc $end
$var reg 32 * immediate [31:0] $end
$var reg 1 + memRead $end
$var reg 1 , memWrite $end
$var reg 1 - regWrite $end
$var reg 5 . rgr1 [4:0] $end
$var reg 5 / rgr2 [4:0] $end
$var reg 5 0 rgw1 [4:0] $end
$scope module alu_unit $end
$var wire 1 1 add_overflow $end
$var wire 4 2 aluCtrl [3:0] $end
$var wire 1 ) aluSrc $end
$var wire 32 3 imm [31:0] $end
$var wire 1 4 sub_overflow $end
$var wire 1 ! zero $end
$var wire 32 5 sum [31:0] $end
$var wire 1 $ overflow $end
$var wire 1 6 op $end
$var wire 32 7 data2 [31:0] $end
$var wire 32 8 data1 [31:0] $end
$var wire 32 9 d2 [31:0] $end
$var wire 1 : carry $end
$var reg 32 ; result [31:0] $end
$scope module addsub $end
$var wire 32 < num2 [31:0] $end
$var wire 1 6 op $end
$var wire 32 = sumO [31:0] $end
$var wire 32 > sum [31:0] $end
$var wire 32 ? num2C [31:0] $end
$var wire 32 @ num1 [31:0] $end
$var wire 1 : carryO $end
$var wire 32 A carry [31:0] $end
$scope begin gen_block[0] $end
$var parameter 2 B i $end
$scope begin genblk1 $end
$scope module addr0 $end
$var wire 1 6 carryI $end
$var wire 1 C carryO $end
$var wire 1 D num1 $end
$var wire 1 E num2 $end
$var wire 1 F sum $end
$upscope $end
$upscope $end
$upscope $end
$scope begin gen_block[1] $end
$var parameter 2 G i $end
$scope begin genblk1 $end
$scope module addrN $end
$var wire 1 H carryI $end
$var wire 1 I carryO $end
$var wire 1 J num1 $end
$var wire 1 K num2 $end
$var wire 1 L sum $end
$upscope $end
$upscope $end
$upscope $end
$scope begin gen_block[2] $end
$var parameter 3 M i $end
$scope begin genblk1 $end
$scope module addrN $end
$var wire 1 N carryI $end
$var wire 1 O carryO $end
$var wire 1 P num1 $end
$var wire 1 Q num2 $end
$var wire 1 R sum $end
$upscope $end
$upscope $end
$upscope $end
$scope begin gen_block[3] $end
$var parameter 3 S i $end
$scope begin genblk1 $end
$scope module addrN $end
$var wire 1 T carryI $end
$var wire 1 U carryO $end
$var wire 1 V num1 $end
$var wire 1 W num2 $end
$var wire 1 X sum $end
$upscope $end
$upscope $end
$upscope $end
$scope begin gen_block[4] $end
$var parameter 4 Y i $end
$scope begin genblk1 $end
$scope module addrN $end
$var wire 1 Z carryI $end
$var wire 1 [ carryO $end
$var wire 1 \ num1 $end
$var wire 1 ] num2 $end
$var wire 1 ^ sum $end
$upscope $end
$upscope $end
$upscope $end
$scope begin gen_block[5] $end
$var parameter 4 _ i $end
$scope begin genblk1 $end
$scope module addrN $end
$var wire 1 ` carryI $end
$var wire 1 a carryO $end
$var wire 1 b num1 $end
$var wire 1 c num2 $end
$var wire 1 d sum $end
$upscope $end
$upscope $end
$upscope $end
$scope begin gen_block[6] $end
$var parameter 4 e i $end
$scope begin genblk1 $end
$scope module addrN $end
$var wire 1 f carryI $end
$var wire 1 g carryO $end
$var wire 1 h num1 $end
$var wire 1 i num2 $end
$var wire 1 j sum $end
$upscope $end
$upscope $end
$upscope $end
$scope begin gen_block[7] $end
$var parameter 4 k i $end
$scope begin genblk1 $end
$scope module addrN $end
$var wire 1 l carryI $end
$var wire 1 m carryO $end
$var wire 1 n num1 $end
$var wire 1 o num2 $end
$var wire 1 p sum $end
$upscope $end
$upscope $end
$upscope $end
$scope begin gen_block[8] $end
$var parameter 5 q i $end
$scope begin genblk1 $end
$scope module addrN $end
$var wire 1 r carryI $end
$var wire 1 s carryO $end
$var wire 1 t num1 $end
$var wire 1 u num2 $end
$var wire 1 v sum $end
$upscope $end
$upscope $end
$upscope $end
$scope begin gen_block[9] $end
$var parameter 5 w i $end
$scope begin genblk1 $end
$scope module addrN $end
$var wire 1 x carryI $end
$var wire 1 y carryO $end
$var wire 1 z num1 $end
$var wire 1 { num2 $end
$var wire 1 | sum $end
$upscope $end
$upscope $end
$upscope $end
$scope begin gen_block[10] $end
$var parameter 5 } i $end
$scope begin genblk1 $end
$scope module addrN $end
$var wire 1 ~ carryI $end
$var wire 1 !" carryO $end
$var wire 1 "" num1 $end
$var wire 1 #" num2 $end
$var wire 1 $" sum $end
$upscope $end
$upscope $end
$upscope $end
$scope begin gen_block[11] $end
$var parameter 5 %" i $end
$scope begin genblk1 $end
$scope module addrN $end
$var wire 1 &" carryI $end
$var wire 1 '" carryO $end
$var wire 1 (" num1 $end
$var wire 1 )" num2 $end
$var wire 1 *" sum $end
$upscope $end
$upscope $end
$upscope $end
$scope begin gen_block[12] $end
$var parameter 5 +" i $end
$scope begin genblk1 $end
$scope module addrN $end
$var wire 1 ," carryI $end
$var wire 1 -" carryO $end
$var wire 1 ." num1 $end
$var wire 1 /" num2 $end
$var wire 1 0" sum $end
$upscope $end
$upscope $end
$upscope $end
$scope begin gen_block[13] $end
$var parameter 5 1" i $end
$scope begin genblk1 $end
$scope module addrN $end
$var wire 1 2" carryI $end
$var wire 1 3" carryO $end
$var wire 1 4" num1 $end
$var wire 1 5" num2 $end
$var wire 1 6" sum $end
$upscope $end
$upscope $end
$upscope $end
$scope begin gen_block[14] $end
$var parameter 5 7" i $end
$scope begin genblk1 $end
$scope module addrN $end
$var wire 1 8" carryI $end
$var wire 1 9" carryO $end
$var wire 1 :" num1 $end
$var wire 1 ;" num2 $end
$var wire 1 <" sum $end
$upscope $end
$upscope $end
$upscope $end
$scope begin gen_block[15] $end
$var parameter 5 =" i $end
$scope begin genblk1 $end
$scope module addrN $end
$var wire 1 >" carryI $end
$var wire 1 ?" carryO $end
$var wire 1 @" num1 $end
$var wire 1 A" num2 $end
$var wire 1 B" sum $end
$upscope $end
$upscope $end
$upscope $end
$scope begin gen_block[16] $end
$var parameter 6 C" i $end
$scope begin genblk1 $end
$scope module addrN $end
$var wire 1 D" carryI $end
$var wire 1 E" carryO $end
$var wire 1 F" num1 $end
$var wire 1 G" num2 $end
$var wire 1 H" sum $end
$upscope $end
$upscope $end
$upscope $end
$scope begin gen_block[17] $end
$var parameter 6 I" i $end
$scope begin genblk1 $end
$scope module addrN $end
$var wire 1 J" carryI $end
$var wire 1 K" carryO $end
$var wire 1 L" num1 $end
$var wire 1 M" num2 $end
$var wire 1 N" sum $end
$upscope $end
$upscope $end
$upscope $end
$scope begin gen_block[18] $end
$var parameter 6 O" i $end
$scope begin genblk1 $end
$scope module addrN $end
$var wire 1 P" carryI $end
$var wire 1 Q" carryO $end
$var wire 1 R" num1 $end
$var wire 1 S" num2 $end
$var wire 1 T" sum $end
$upscope $end
$upscope $end
$upscope $end
$scope begin gen_block[19] $end
$var parameter 6 U" i $end
$scope begin genblk1 $end
$scope module addrN $end
$var wire 1 V" carryI $end
$var wire 1 W" carryO $end
$var wire 1 X" num1 $end
$var wire 1 Y" num2 $end
$var wire 1 Z" sum $end
$upscope $end
$upscope $end
$upscope $end
$scope begin gen_block[20] $end
$var parameter 6 [" i $end
$scope begin genblk1 $end
$scope module addrN $end
$var wire 1 \" carryI $end
$var wire 1 ]" carryO $end
$var wire 1 ^" num1 $end
$var wire 1 _" num2 $end
$var wire 1 `" sum $end
$upscope $end
$upscope $end
$upscope $end
$scope begin gen_block[21] $end
$var parameter 6 a" i $end
$scope begin genblk1 $end
$scope module addrN $end
$var wire 1 b" carryI $end
$var wire 1 c" carryO $end
$var wire 1 d" num1 $end
$var wire 1 e" num2 $end
$var wire 1 f" sum $end
$upscope $end
$upscope $end
$upscope $end
$scope begin gen_block[22] $end
$var parameter 6 g" i $end
$scope begin genblk1 $end
$scope module addrN $end
$var wire 1 h" carryI $end
$var wire 1 i" carryO $end
$var wire 1 j" num1 $end
$var wire 1 k" num2 $end
$var wire 1 l" sum $end
$upscope $end
$upscope $end
$upscope $end
$scope begin gen_block[23] $end
$var parameter 6 m" i $end
$scope begin genblk1 $end
$scope module addrN $end
$var wire 1 n" carryI $end
$var wire 1 o" carryO $end
$var wire 1 p" num1 $end
$var wire 1 q" num2 $end
$var wire 1 r" sum $end
$upscope $end
$upscope $end
$upscope $end
$scope begin gen_block[24] $end
$var parameter 6 s" i $end
$scope begin genblk1 $end
$scope module addrN $end
$var wire 1 t" carryI $end
$var wire 1 u" carryO $end
$var wire 1 v" num1 $end
$var wire 1 w" num2 $end
$var wire 1 x" sum $end
$upscope $end
$upscope $end
$upscope $end
$scope begin gen_block[25] $end
$var parameter 6 y" i $end
$scope begin genblk1 $end
$scope module addrN $end
$var wire 1 z" carryI $end
$var wire 1 {" carryO $end
$var wire 1 |" num1 $end
$var wire 1 }" num2 $end
$var wire 1 ~" sum $end
$upscope $end
$upscope $end
$upscope $end
$scope begin gen_block[26] $end
$var parameter 6 !# i $end
$scope begin genblk1 $end
$scope module addrN $end
$var wire 1 "# carryI $end
$var wire 1 ## carryO $end
$var wire 1 $# num1 $end
$var wire 1 %# num2 $end
$var wire 1 &# sum $end
$upscope $end
$upscope $end
$upscope $end
$scope begin gen_block[27] $end
$var parameter 6 '# i $end
$scope begin genblk1 $end
$scope module addrN $end
$var wire 1 (# carryI $end
$var wire 1 )# carryO $end
$var wire 1 *# num1 $end
$var wire 1 +# num2 $end
$var wire 1 ,# sum $end
$upscope $end
$upscope $end
$upscope $end
$scope begin gen_block[28] $end
$var parameter 6 -# i $end
$scope begin genblk1 $end
$scope module addrN $end
$var wire 1 .# carryI $end
$var wire 1 /# carryO $end
$var wire 1 0# num1 $end
$var wire 1 1# num2 $end
$var wire 1 2# sum $end
$upscope $end
$upscope $end
$upscope $end
$scope begin gen_block[29] $end
$var parameter 6 3# i $end
$scope begin genblk1 $end
$scope module addrN $end
$var wire 1 4# carryI $end
$var wire 1 5# carryO $end
$var wire 1 6# num1 $end
$var wire 1 7# num2 $end
$var wire 1 8# sum $end
$upscope $end
$upscope $end
$upscope $end
$scope begin gen_block[30] $end
$var parameter 6 9# i $end
$scope begin genblk1 $end
$scope module addrN $end
$var wire 1 :# carryI $end
$var wire 1 ;# carryO $end
$var wire 1 <# num1 $end
$var wire 1 =# num2 $end
$var wire 1 ># sum $end
$upscope $end
$upscope $end
$upscope $end
$scope begin gen_block[31] $end
$var parameter 6 ?# i $end
$scope begin genblk1 $end
$scope module addrN $end
$var wire 1 @# carryI $end
$var wire 1 A# carryO $end
$var wire 1 B# num1 $end
$var wire 1 C# num2 $end
$var wire 1 D# sum $end
$upscope $end
$upscope $end
$upscope $end
$upscope $end
$upscope $end
$scope module dm $end
$var wire 32 E# address [31:0] $end
$var wire 1 + memRead $end
$var wire 1 , memWrite $end
$var wire 32 F# writeData [31:0] $end
$var reg 32 G# readData [31:0] $end
$var integer 32 H# i [31:0] $end
$upscope $end
$scope module rf $end
$var wire 5 I# rgr1 [4:0] $end
$var wire 5 J# rgr2 [4:0] $end
$var wire 5 K# rgw1 [4:0] $end
$var wire 32 L# rgw1data [31:0] $end
$var wire 1 - write $end
$var reg 32 M# rg1data [31:0] $end
$var reg 32 N# rg2data [31:0] $end
$var integer 32 O# i [31:0] $end
$upscope $end
$upscope $end
$enddefinitions $end
$comment Show the parameter values. $end
$dumpall
b11111 ?#
b11110 9#
b11101 3#
b11100 -#
b11011 '#
b11010 !#
b11001 y"
b11000 s"
b10111 m"
b10110 g"
b10101 a"
b10100 ["
b10011 U"
b10010 O"
b10001 I"
b10000 C"
b1111 ="
b1110 7"
b1101 1"
b1100 +"
b1011 %"
b1010 }
b1001 w
b1000 q
b111 k
b110 e
b101 _
b100 Y
b11 S
b10 M
b1 G
b0 B
$end
#0
$dumpvars
b100000 O#
b0 N#
b0 M#
b0 L#
b0 K#
b0 J#
b0 I#
b10000000000 H#
bx G#
b0 F#
b0 E#
0D#
0C#
0B#
0A#
0@#
0>#
0=#
0<#
0;#
0:#
08#
07#
06#
05#
04#
02#
01#
00#
0/#
0.#
0,#
0+#
0*#
0)#
0(#
0&#
0%#
0$#
0##
0"#
0~"
0}"
0|"
0{"
0z"
0x"
0w"
0v"
0u"
0t"
0r"
0q"
0p"
0o"
0n"
0l"
0k"
0j"
0i"
0h"
0f"
0e"
0d"
0c"
0b"
0`"
0_"
0^"
0]"
0\"
0Z"
0Y"
0X"
0W"
0V"
0T"
0S"
0R"
0Q"
0P"
0N"
0M"
0L"
0K"
0J"
0H"
0G"
0F"
0E"
0D"
0B"
0A"
0@"
0?"
0>"
0<"
0;"
0:"
09"
08"
06"
05"
04"
03"
02"
00"
0/"
0."
0-"
0,"
0*"
0)"
0("
0'"
0&"
0$"
0#"
0""
0!"
0~
0|
0{
0z
0y
0x
0v
0u
0t
0s
0r
0p
0o
0n
0m
0l
0j
0i
0h
0g
0f
0d
0c
0b
0a
0`
0^
0]
0\
0[
0Z
0X
0W
0V
0U
0T
0R
0Q
0P
0O
0N
0L
0K
0J
0I
0H
0F
0E
0D
0C
b0 A
b0 @
b0 ?
b0 >
b0 =
b0 <
b0 ;
0:
b0 9
b0 8
b0 7
06
b0 5
04
b0 3
b0 2
01
b0 0
b0 /
b0 .
0-
0,
0+
b0 *
0)
b0 (
b0 '
b0 &
bx %
0$
b0 #
b0 "
1!
$end
#10000
0!
b101 &
b101 ;
b101 F#
b101 L#
1R
b101 5
b101 =
b101 >
1F
1Q
1E
b101 ?
b101 9
b101 <
b10100 0
b10100 K#
b101 *
b101 3
1)
#20000
1-
#30000
0-
#40000
b10 &
b10 ;
b10 F#
b10 L#
0R
1L
b10 5
b10 =
b10 >
0F
0Q
1K
0E
b10 ?
b10 9
b10 <
b10101 0
b10101 K#
b10 *
b10 3
#50000
1-
#60000
0-
#70000
b10110 0
b10110 K#
#80000
1-
#90000
0-
#100000
b100 &
b100 ;
b100 F#
b100 L#
1R
b100 5
b100 =
b100 >
0L
1Q
0K
b100 ?
b100 9
b100 <
b10111 0
b10111 K#
b100 *
b100 3
#110000
1-
#120000
0-
#130000
b111 &
b111 ;
b111 F#
b111 L#
1L
b111 5
b111 =
b111 >
1F
1K
1E
b111 ?
b111 9
b111 <
b11000 0
b11000 K#
b111 *
b111 3
#140000
1-
#150000
0-
#160000
b1001 &
b1001 ;
b1001 F#
b1001 L#
1X
0R
b1001 5
b1001 =
b1001 >
0L
1W
0Q
0K
b1001 ?
b1001 9
b1001 <
b11001 0
b11001 K#
b1001 *
b1001 3
#170000
1-
#180000
0-
#190000
1!
b0 &
b0 ;
b0 F#
b0 L#
0X
b0 5
b0 =
b0 >
0F
0W
0E
b0 ?
b0 9
b0 <
b11111 0
b11111 K#
b0 *
b0 3
#200000
1-
#210000
0-
#220000
0!
b101 &
b101 ;
b101 F#
b101 L#
1R
b101 5
b101 =
b101 >
1F
1Q
1E
b101 ?
b101 9
b101 <
b101 "
b101 7
b101 N#
b10100 /
b10100 J#
b11111 .
b11111 I#
0)
#240000
1-
#250000
0-
#260000
1L
0N
0I
0X
0!
0T
0H
0O
b111 &
b111 ;
b111 F#
b111 L#
b0 A
0C
0Q
1K
0E
1R
b111 5
b111 =
b111 >
1F
b10 ?
b10 9
b10 <
1P
1D
b10 "
b10 7
b10 N#
b101 #
b101 8
b101 @
b101 M#
b10101 /
b10101 J#
#280000
1-
#290000
0-
#300000
1X
1T
1O
0R
1N
b1001 &
b1001 ;
b1001 F#
b1001 L#
b110 A
1I
b1001 5
b1001 =
b1001 >
0L
1J
b111 #
b111 8
b111 @
b111 M#
b10110 /
b10110 J#
#320000
1-
#330000
0-
#340000
0^
0Z
0T
0N
0U
0O
b1101 &
b1101 ;
b1101 F#
b1101 L#
b0 A
0I
1Q
0K
1X
1R
b1101 5
b1101 =
b1101 >
0L
b100 ?
b100 9
b100 <
1V
0P
0J
b100 "
b100 7
b100 N#
b1001 #
b1001 8
b1001 @
b1001 M#
b10111 /
b10111 J#
#360000
1-
#370000
0-
#380000
0!
1N
1^
1I
1Z
1U
1H
1C
0X
0L
0F
1T
b10100 &
b10100 ;
b10100 F#
b10100 L#
b1111 A
1O
1K
1E
b10100 5
b10100 =
b10100 >
1R
b111 ?
b111 9
b111 <
1P
b111 "
b111 7
b111 N#
b1101 #
b1101 8
b1101 @
b1101 M#
b11000 /
b11000 J#
#400000
1-
#410000
0-
#420000
0T
0O
0N
0d
1R
0I
0`
0Z
0H
0[
0U
b11101 &
b11101 ;
b11101 F#
b11101 L#
b0 A
0C
1W
0Q
0K
1^
1X
b11101 5
b11101 =
b11101 >
1F
b1001 ?
b1001 9
b1001 <
1\
0V
0D
b1001 "
b1001 7
b1001 N#
b10100 #
b10100 8
b10100 @
b10100 M#
b11001 /
b11001 J#
#440000
1-
#450000
0-
