verilog_codes/Multiplexer/NXOR_Multiplexer_Devan.v
`timescale 1ns/1ns
module mux_nxor (
    input a, b, sel,
    output y
);
    
    wire nxor_ab;
    xnor(nxor_ab, a, b);
    
    assign y = sel ? nxor_ab : 1'b0;
    
endmodule

module testb;
    reg a, b, sel;
    wire y;
    
    mux_nxor uut (.a(a), .b(b), .sel(sel), .y(y));

    initial begin
        $dumpfile("test1.vcd");
        $dumpvars(); // Display GTKWave
        $monitor("a=%b, b=%b, sel=%b, y=%b", a, b, sel, y);
        
        a = 0; b = 0; sel = 0;
        #10 a = 0; b = 0; sel = 1;
        #10 a = 0; b = 1; sel = 0;
        #10 a = 0; b = 1; sel = 1;
        #10 a = 1; b = 0; sel = 0;
        #10 a = 1; b = 0; sel = 1;
        #10 a = 1; b = 1; sel = 0;
        #10 a = 1; b = 1; sel = 1;
        #10 $finish;
    end
endmodule

verilog_codes/Multiplexer/NXOR.vcd
$date
	Tue Mar 04 11:40:00 2025
$end
$version
	Icarus Verilog
$end
$timescale
	1ns
$end
$scope module testb $end
$var wire 1 ! y $end
$var reg 1 " a $end
$var reg 1 # b $end
$var reg 1 $ sel $end
$scope module uut $end
$var wire 1 " a $end
$var wire 1 # b $end
$var wire 1 % nxor_ab $end
$var wire 1 $ sel $end
$var wire 1 ! y $end
$upscope $end
$upscope $end
$enddefinitions $end
$comment Show the parameter values. $end
$dumpall
$end
#0
$dumpvars
1%
0$
0#
0"
0!
$end
#10
1!
1$
#20
0!
0%
0$
1#
#30
1$
#40
0$
0#
1"
#50
1$
#60
1%
0$
1#
#70
1!
1$
