verilog_codes/1-bit_FullAdder_Evan.v
`timescale 1ns/1ns

module full_adder (
    input A, B, Cin,
    output S, Cout
);

    assign S = A ^ B ^ Cin;
    assign Cout = (A & B) | (A & Cin) | (B & Cin);

endmodule

// Testbench for the full adder
module testbench;
    reg A, B, Cin;
    wire S, Cout;

    full_adder uut (.A(A), .B(B), .Cin(Cin), .S(S), .Cout(Cout));

    initial begin
        $dumpfile("full_adder.vcd");
        $dumpvars(0, testbench);

        $monitor("A=%b, B=%b, Cin=%b -> S=%b, Cout=%b", A, B, Cin, S, Cout);

        A = 0; B = 0; Cin = 0; #10;
        A = 0; B = 0; Cin = 1; #10;
        A = 0; B = 1; Cin = 0; #10;
        A = 0; B = 1; Cin = 1; #10;
        A = 1; B = 0; Cin = 0; #10;
        A = 1; B = 0; Cin = 1; #10;
        A = 1; B = 1; Cin = 0; #10;
        A = 1; B = 1; Cin = 1; #10;

        $finish;
    end
endmodule

verilog_codes/full_adder.vcd
$date
	Fri Feb 28 14:17:01 2025
$end
$version
	Icarus Verilog
$end
$timescale
	1ns
$end
$scope module testbench $end
$var wire 1 ! S $end
$var wire 1 " Cout $end
$var reg 1 # A $end
$var reg 1 $ B $end
$var reg 1 % Cin $end
$scope module uut $end
$var wire 1 # A $end
$var wire 1 $ B $end
$var wire 1 % Cin $end
$var wire 1 " Cout $end
$var wire 1 ! S $end
$upscope $end
$upscope $end
$enddefinitions $end
$comment Show the parameter values. $end
$dumpall
$end
#0
$dumpvars
0%
0$
0#
0"
0!
$end
#10
1!
1%
#20
0%
1$
#30
1"
0!
1%
#40
0"
1!
0%
0$
1#
#50
1"
0!
1%
#60
0%
1$
#70
1!
1%
